{
  "hash": "b3723ead",
  "configHash": "19a6bca3",
  "lockfileHash": "bd3bc180",
  "browserHash": "8f2342c2",
  "optimized": {
    "vue": {
      "src": "../../../../node_modules/vue/dist/vue.runtime.esm-bundler.js",
      "file": "vue.js",
      "fileHash": "48a4b7ac",
      "needsInterop": false
    },
    "vitepress > @vue/devtools-api": {
      "src": "../../../../node_modules/@vue/devtools-api/lib/esm/index.js",
      "file": "vitepress___@vue_devtools-api.js",
      "fileHash": "dcbaaaaf",
      "needsInterop": false
    },
    "vitepress > @vueuse/core": {
      "src": "../../../../node_modules/@vueuse/core/index.mjs",
      "file": "vitepress___@vueuse_core.js",
      "fileHash": "1907b464",
      "needsInterop": false
    },
    "vitepress > @vueuse/integrations/useFocusTrap": {
      "src": "../../../../node_modules/@vueuse/integrations/useFocusTrap.mjs",
      "file": "vitepress___@vueuse_integrations_useFocusTrap.js",
      "fileHash": "0f5545d9",
      "needsInterop": false
    },
    "vitepress > mark.js/src/vanilla.js": {
      "src": "../../../../node_modules/mark.js/src/vanilla.js",
      "file": "vitepress___mark__js_src_vanilla__js.js",
      "fileHash": "b91d1b06",
      "needsInterop": false
    },
    "vitepress > minisearch": {
      "src": "../../../../node_modules/minisearch/dist/es/index.js",
      "file": "vitepress___minisearch.js",
      "fileHash": "068d4e46",
      "needsInterop": false
    },
    "medium-zoom": {
      "src": "../../../../node_modules/medium-zoom/dist/medium-zoom.esm.js",
      "file": "medium-zoom.js",
      "fileHash": "281d7c9d",
      "needsInterop": false
    },
    "ant-design-vue": {
      "src": "../../../../node_modules/ant-design-vue/es/index.js",
      "file": "ant-design-vue.js",
      "fileHash": "932895e6",
      "needsInterop": false
    },
    "@mdit-vue/shared": {
      "src": "../../../../node_modules/@mdit-vue/shared/dist/index.mjs",
      "file": "@mdit-vue_shared.js",
      "fileHash": "14fbe40a",
      "needsInterop": false
    },
    "@giscus/vue": {
      "src": "../../../../node_modules/@giscus/vue/dist/index.mjs",
      "file": "@giscus_vue.js",
      "fileHash": "8e0a8634",
      "needsInterop": false
    },
    "@ant-design/icons-vue": {
      "src": "../../../../node_modules/@ant-design/icons-vue/es/index.js",
      "file": "@ant-design_icons-vue.js",
      "fileHash": "f37d517f",
      "needsInterop": false
    },
    "prismjs": {
      "src": "../../../../node_modules/prismjs/prism.js",
      "file": "prismjs.js",
      "fileHash": "acead67a",
      "needsInterop": true
    },
    "dayjs": {
      "src": "../../../../node_modules/dayjs/dayjs.min.js",
      "file": "dayjs.js",
      "fileHash": "8606ba5c",
      "needsInterop": true
    }
  },
  "chunks": {
    "giscus-aTimukGI-Z5RBZEUI": {
      "file": "giscus-aTimukGI-Z5RBZEUI.js"
    },
    "chunk-O7A6KEVD": {
      "file": "chunk-O7A6KEVD.js"
    },
    "chunk-MDZOBHN3": {
      "file": "chunk-MDZOBHN3.js"
    },
    "chunk-TL4KESHX": {
      "file": "chunk-TL4KESHX.js"
    },
    "chunk-ZS7NZCD4": {
      "file": "chunk-ZS7NZCD4.js"
    }
  }
}