{"views_daily-notes_daily-notes.md":"C33uLAO5","views_apps_translate.md":"OJw7vN7d","index.md":"B7xpHeRq","views_about_about.md":"BUSvEEpV","views_daily-notes_2023_001.md":"DQUyH-O_","views_daily-notes_2024_001.md":"Bnen2HTd","views_apps_girls.md":"Y7w2GvdW","views_nav_nav.md":"C8uqFnmO","views_note_angular.md":"DIU6jbXm","views_note_git.md":"BcKpyOIv","views_note_unocss.md":"u4FnoJKd","views_note_vuepress.md":"DkNJa_Pk","views_share_css_experience.md":"D9jtT-H3","views_share_css_shadow.md":"DMfEbP07","views_share_css_background.md":"CfNvCNCw","views_share_javascript_skill.md":"BFtD5eDZ","views_note_electron.md":"C-qJI2PK","views_note_vitepress.md":"Dh4V0165","views_tools_vuedocpreview.md":"BwY3Oquj","views_share_css_generate.md":"DLNrVAre","views_share_css_other.md":"BSNCNlFf","views_tools_moment.md":"CpiIgMlX","views_note_vitepress-import.md":"CKIsj2bN","views_share_css_reset.md":"BssSw9_W","views_note_react.md":"C9Y9Ykj6","views_share_css_effect.md":"DeC64squ","views_share_css_flex.md":"LRSwjOMX","views_note_sass.md":"DscLgjPV","views_share_css_text.md":"C0eDtfnx","views_share_css_3d.md":"DfLfsj6c","views_note_vue3.md":"D0E4XWWX","views_share_css_loading.md":"Bo4RDRhq","views_share_javascript_process.md":"CCu9fhCo","views_tools_aceeditor.md":"CA4bzFZc","views_note_vue3-quick-start.md":"BfbVQ_bg","views_note_node.md":"SkdJ6Wbl","views_share_css_grid.md":"ENZqp37x","views_share_javascript_tool.md":"d4liQmd9","views_note_python.md":"lLfHUfcE"}
